MANIFEST.in
README.md
setup.py
pygui_cli.egg-info/PKG-INFO
pygui_cli.egg-info/SOURCES.txt
pygui_cli.egg-info/dependency_links.txt
pygui_cli.egg-info/entry_points.txt
pygui_cli.egg-info/not-zip-safe
pygui_cli.egg-info/requires.txt
pygui_cli.egg-info/top_level.txt
source/LICENSE
source/Ui_main.py
source/__init__.py
source/main.py
source/main.ui
source/main_preinit_ui.py
source/pygui_cli.e4p
source/resource.qrc
source/resource_rc.py
source/Config/__init__.py
source/Config/log.txt
source/Config/settings.ini
source/Styles/CommonHelper.py
source/Styles/Ui_style.py
source/Styles/__init__.py
source/Styles/style.css
source/Styles/style.styl
source/Styles/CustomTitlebar/Ui_framelesswindow.py
source/Styles/CustomTitlebar/__init__.py
source/Styles/CustomTitlebar/framelesswindow.py
source/Styles/CustomTitlebar/framelesswindow.qrc
source/Styles/CustomTitlebar/framelesswindow.ui
source/Styles/CustomTitlebar/framelesswindow_local.ui
source/Styles/CustomTitlebar/framelesswindow_rc.py
source/Styles/CustomTitlebar/windowdragger.py
source/Styles/CustomTitlebar/button_Ima/__init__.py
source/Styles/CustomTitlebar/button_Ima/git.ico
source/Styles/CustomTitlebar/button_Ima/icon_window_close.png
source/Styles/CustomTitlebar/button_Ima/icon_window_maximize.png
source/Styles/CustomTitlebar/button_Ima/icon_window_minimize.png
source/Styles/CustomTitlebar/button_Ima/icon_window_restore.png
source/Styles/rc/Hmovetoolbar.png
source/Styles/rc/Hsepartoolbar.png
source/Styles/rc/Vmovetoolbar.png
source/Styles/rc/Vsepartoolbar.png
source/Styles/rc/__init__.py
source/Styles/rc/branch_closed-on.png
source/Styles/rc/branch_closed.png
source/Styles/rc/branch_open-on.png
source/Styles/rc/branch_open.png
source/Styles/rc/checkbox_checked.png
source/Styles/rc/checkbox_checked_disabled.png
source/Styles/rc/checkbox_checked_focus.png
source/Styles/rc/checkbox_indeterminate.png
source/Styles/rc/checkbox_indeterminate_disabled.png
source/Styles/rc/checkbox_indeterminate_focus.png
source/Styles/rc/checkbox_unchecked.png
source/Styles/rc/checkbox_unchecked_disabled.png
source/Styles/rc/checkbox_unchecked_focus.png
source/Styles/rc/close-hover.png
source/Styles/rc/close-pressed.png
source/Styles/rc/close.png
source/Styles/rc/down_arrow.png
