Metadata-Version: 2.1
Name: pygui-cli
Version: 0.0.15
Summary: pyqt5 & pyside2 template.
Home-page: https://github.com/625781186/pygui_cli
Author: Lin JH
Author-email: 625781186@qq.com
License: GPL-3.0
Keywords: python、PyQt5、template
Platform: UNKNOWN
